CHANGES.txt
MANIFEST.in
README.rst
setup.py
src/jspack/__init__.py
src/jspack.egg-info/PKG-INFO
src/jspack.egg-info/SOURCES.txt
src/jspack.egg-info/dependency_links.txt
src/jspack.egg-info/entry_points.txt
src/jspack.egg-info/not-zip-safe
src/jspack.egg-info/top_level.txt