Metadata-Version: 1.0
Name: jspack
Version: 0.3
Summary: A simple tool for javascript packging using config files
Home-page: http://pypi.python.org/pypi/jspack
Author: Pablo Caro
Author-email: pcaro@yaco.es
License: MIT
Keywords: javascript tools
Platform: UNKNOWN
Classifier: Programming Language :: JavaScript
Classifier: Topic :: Software Development :: Build Tools
Classifier: Topic :: Software Development :: Code Generators
Classifier: License :: OSI Approved :: MIT License
